MANIFEST.in
README.rst
setup.py
collective/__init__.py
collective.portlet.personaltools.egg-info/PKG-INFO
collective.portlet.personaltools.egg-info/SOURCES.txt
collective.portlet.personaltools.egg-info/dependency_links.txt
collective.portlet.personaltools.egg-info/entry_points.txt
collective.portlet.personaltools.egg-info/namespace_packages.txt
collective.portlet.personaltools.egg-info/not-zip-safe
collective.portlet.personaltools.egg-info/requires.txt
collective.portlet.personaltools.egg-info/top_level.txt
collective/portlet/__init__.py
collective/portlet/personaltools/__init__.py
collective/portlet/personaltools/configure.zcml
collective/portlet/personaltools/personaltools.pt
collective/portlet/personaltools/personaltools.py
collective/portlet/personaltools/version.txt
collective/portlet/personaltools/profiles/default/metadata.xml
collective/portlet/personaltools/profiles/default/portlets.xml
collective/portlet/personaltools/tests/__init__.py
collective/portlet/personaltools/tests/base.py
collective/portlet/personaltools/tests/test_portlet.py
docs/HISTORY.txt
docs/INSTALL.txt
docs/LICENSE.GPL
docs/LICENSE.txt