Metadata-Version: 1.1
Name: collective.portlet.personaltools
Version: 1.0
Summary: Plone personal tools portlet
Home-page: https://github.com/collective/collective.portlet.personaltools
Author: Bogdan Girman
Author-email: bogdan.girman@gmail.com
License: GPL
Keywords: portlet personal tools
Platform: UNKNOWN
Classifier: Framework :: Plone
Classifier: Programming Language :: Python
